execnb/__init__.py
execnb/_modidx.py
execnb/nbio.py
execnb/shell.py
execnb-0.1.18.dist-info/licenses/LICENSE
execnb-0.1.18.dist-info/METADATA
execnb-0.1.18.dist-info/WHEEL
execnb-0.1.18.dist-info/entry_points.txt
execnb-0.1.18.dist-info/top_level.txt
execnb-0.1.18.dist-info/RECORD
