Metadata-Version: 2.4
Name: execnb
Version: 0.1.18
Summary: A description of your project
Home-page: https://github.com/AnswerDotAI/execnb/
Author: Jeremy Howard
Author-email: j@fast.ai
License: Apache Software License 2.0
Keywords: some keywords
Classifier: Development Status :: 3 - Alpha
Classifier: Intended Audience :: Developers
Classifier: Natural Language :: English
Classifier: Programming Language :: Python :: 3.7
Classifier: Programming Language :: Python :: 3.8
Classifier: License :: OSI Approved :: Apache Software License
Requires-Python: >=3.7
License-File: LICENSE
Requires-Dist: fastcore>=1.10.4
Requires-Dist: ipython
Provides-Extra: dev
Requires-Dist: matplotlib; extra == "dev"
Requires-Dist: Pillow; extra == "dev"
Requires-Dist: mistletoe; extra == "dev"
Dynamic: author
Dynamic: author-email
Dynamic: classifier
Dynamic: description
Dynamic: description-content-type
Dynamic: home-page
Dynamic: keywords
Dynamic: license
Dynamic: license-file
Dynamic: provides-extra
Dynamic: requires-dist
Dynamic: requires-python
Dynamic: summary
